LICENSE
README.md
config.py
magani_app.py
magani_server.py
assets/favicon.ico
assets/mg.jpg
magani/__init__.py
magani/delete_test_case.py
magani/export_text_case.py
magani/home.py
magani/project.py
magani/run_test_case.py
magani/auth/__init__.py
magani/auth/auth.py
magani/http/__init__.py
magani/http/http_client.py
magani/utils/__init__.py
magani/utils/card_util.py
magani/utils/exception.py
magani/utils/file_util.py
magani/utils/modal_util.py
magani-2022.2.28.data/data/assets/favicon.ico
magani-2022.2.28.data/data/assets/mg.jpg
magani-2022.2.28.data/scripts/magani.bat
magani-2022.2.28.data/scripts/magani.sh
magani.egg-info/PKG-INFO
magani.egg-info/SOURCES.txt
magani.egg-info/dependency_links.txt
magani.egg-info/requires.txt
magani.egg-info/top_level.txt
script/magani.bat
script/magani.sh
magani-2022.2.28.dist-info/LICENSE
magani-2022.2.28.dist-info/METADATA
magani-2022.2.28.dist-info/WHEEL
magani-2022.2.28.dist-info/top_level.txt
magani-2022.2.28.dist-info/RECORD
